{
  "farm": {
    "name": "My Farm",
    "level": 1
  },

  "money": {
    "ecus": 1500
  },

  "buildings": {
    "chickenHouse": {
      "capacity": 60,
      "chickens": [
        {
          "id": 1, "type": "cock", "age": 5, "weight": 2.5,
          "clean": true, "healthy": true, "fed": true, "watered": true
        },
        {
          "id": 2, "type": "chicken", "age": 5, "weight": 2.5,
          "clean": true, "healthy": true, "fed": true, "watered": true
        },
        {
          "id": 3, "type": "chicken", "age": 5, "weight": 2.5,
          "clean": true, "healthy": true, "fed": true, "watered": true
        },
        {
          "id": 4, "type": "chicken", "age": 5, "weight": 2.5,
          "clean": true, "healthy": true, "fed": true, "watered": true
        }
      ]
    },

    "rabbitHouse": {
      "capacity": 50,
      "babyRabbits": [
        { "id": 1, "age": 1, "stage": "baby", "alive": true },
        { "id": 2, "age": 1, "stage": "baby", "alive": true },
        { "id": 3, "age": 2, "stage": "small", "alive": true },
        { "id": 4, "age": 2, "stage": "small", "alive": true },
        { "id": 5, "age": 3, "stage": "small", "alive": true },
        { "id": 6, "age": 3, "stage": "big", "alive": true },
        { "id": 7, "age": 3, "stage": "big", "alive": true },
        { "id": 8, "age": 3, "stage": "big", "alive": true }
      ],
      "adultsRabbits": [],
      "clean": true,
      "healthy": true,
      "fed": true,
      "watered": true
    },

    "meadow": {
      "cow": {
        "id": 1, "age": 0, "weight": 1,
        "clean": true, "healthy": true, "fed": true, "watered": true, "milkStored": 0
      }
    }
  },

  "storage": {
    "foodBags": 0,
    "waterBuckets": 0,
    "soap": 0,
    "syringes": 0,
    "strawBales": 0
  }
}